{
  "65637ba5": {
    "url": "/assets/images/static-pages-trade-hero.jpeg",
    "alt": ""
  },
  "a123b68": {
    "url": "/assets/images/jane-beiles-9456-2.jpg",
    "alt": ""
  },
  "-1f79531f": {
    "url": "/assets/images/01img6.jpg",
    "alt": ""
  },
  "6614f82": {
    "url": "/assets/images/hagenblackbl.svg",
    "alt": ""
  },
  "246f5c": {
    "url": "/assets/images/martha.jpg",
    "alt": ""
  },
  "39a6ddfd": {
    "url": "/assets/images/03_process7.jpg",
    "alt": ""
  },
  "29c93051": {
    "url": "/assets/images/abclogo-01.svg",
    "alt": ""
  },
  "-1ec359c0": {
    "url": "/assets/images/herossocial_0003_layer-2.jpg",
    "alt": ""
  }
}